fds/__init__.py
fds/sdk/__init__.py
fds/sdk/ProcuretoPayAPISCIM/__init__.py
fds/sdk/ProcuretoPayAPISCIM/api_client.py
fds/sdk/ProcuretoPayAPISCIM/configuration.py
fds/sdk/ProcuretoPayAPISCIM/exceptions.py
fds/sdk/ProcuretoPayAPISCIM/model_utils.py
fds/sdk/ProcuretoPayAPISCIM/rest.py
fds/sdk/ProcuretoPayAPISCIM/api/__init__.py
fds/sdk/ProcuretoPayAPISCIM/api/federations_api.py
fds/sdk/ProcuretoPayAPISCIM/api/file_manager_audit_api.py
fds/sdk/ProcuretoPayAPISCIM/api/firm_descriptions_api.py
fds/sdk/ProcuretoPayAPISCIM/api/groups_api.py
fds/sdk/ProcuretoPayAPISCIM/api/locations_api.py
fds/sdk/ProcuretoPayAPISCIM/api/products_api.py
fds/sdk/ProcuretoPayAPISCIM/api/schemas_api.py
fds/sdk/ProcuretoPayAPISCIM/api/service_provider_configuration_api.py
fds/sdk/ProcuretoPayAPISCIM/api/user_classes_api.py
fds/sdk/ProcuretoPayAPISCIM/api/user_positions_api.py
fds/sdk/ProcuretoPayAPISCIM/api/users_api.py
fds/sdk/ProcuretoPayAPISCIM/apis/__init__.py
fds/sdk/ProcuretoPayAPISCIM/model/__init__.py
fds/sdk/ProcuretoPayAPISCIM/model/authentication_scheme.py
fds/sdk/ProcuretoPayAPISCIM/model/error.py
fds/sdk/ProcuretoPayAPISCIM/model/federation_resource.py
fds/sdk/ProcuretoPayAPISCIM/model/federation_resource_list.py
fds/sdk/ProcuretoPayAPISCIM/model/federation_resource_location.py
fds/sdk/ProcuretoPayAPISCIM/model/federation_resource_reference.py
fds/sdk/ProcuretoPayAPISCIM/model/federation_resource_reference_assertion_value.py
fds/sdk/ProcuretoPayAPISCIM/model/federation_resource_user.py
fds/sdk/ProcuretoPayAPISCIM/model/federation_resource_user_assertion_value.py
fds/sdk/ProcuretoPayAPISCIM/model/file_manager_audit.py
fds/sdk/ProcuretoPayAPISCIM/model/file_manager_audit_item.py
fds/sdk/ProcuretoPayAPISCIM/model/file_manager_audit_item_additional_property.py
fds/sdk/ProcuretoPayAPISCIM/model/file_manager_audit_item_additional_property_entity.py
fds/sdk/ProcuretoPayAPISCIM/model/file_manager_audit_item_additional_property_permission_override.py
fds_sdk_procuretopayapiscim-0.23.2.dist-info/licenses/LICENSE
fds_sdk_procuretopayapiscim-0.23.2.dist-info/METADATA
fds_sdk_procuretopayapiscim-0.23.2.dist-info/WHEEL
fds_sdk_procuretopayapiscim-0.23.2.dist-info/top_level.txt
fds_sdk_procuretopayapiscim-0.23.2.dist-info/RECORD
